section_3/arm7Cpu/cpu.v
module simple_cpu(
    input clk
);

    // ROM: byte-addressable
    reg [7:0] rom [0:1023];     // 1KB ROM

    // 16 registers, 32-bit
    reg [31:0] regfile [0:15];

    reg [31:0] pc;

    // temporary bytes
    reg [7:0] opcode;
    reg [7:0] b1, b2, b3;

    integer i;

    initial begin
        $readmemh("program.mem", rom);

        for (i = 0; i < 1024; i = i + 1) begin
          if (rom[i] === 8'hxx || rom[i] === 8'hXX) begin
            rom[i] = 8'h00;
          end
        end

        pc = 0;

        for (i = 0; i < 16; i = i + 1)
            regfile[i] = 0;

        for (i = 0; i < 100; i = i + 1)
           $display("%0d: %02x", i, rom[i]);
    end


    always @(posedge clk) begin
        opcode = rom[pc];

        case (opcode)

        8'h01: begin
            // MOV Rd, #imm
            b1 = rom[pc + 1];
            b2 = rom[pc + 2];
            regfile[b1[3:0]] <= {24'b0, b2};
            pc <= pc + 3;
        end

        8'h02: begin
            // ADD Rd, Rn, Rm
            b1 = rom[pc + 1];
            b2 = rom[pc + 2];
            b3 = rom[pc + 3];
            regfile[b1[3:0]] <= regfile[b2[3:0]] + regfile[b3[3:0]];
            pc <= pc + 4;
        end

        8'h03: begin
            // SUB Rd, Rn, Rm
            b1 = rom[pc + 1];
            b2 = rom[pc + 2];
            b3 = rom[pc + 3];
            regfile[b1[3:0]] <= regfile[b2[3:0]] - regfile[b3[3:0]];
            pc <= pc + 4;
        end

        8'h04: begin
            // OUT Rn
            b1 = rom[pc + 1];
            $write("%c", regfile[b1[3:0]][7:0]);
            pc <= pc + 2;
        end

        8'h10: begin
            // B offset
            b1 = rom[pc + 1];
            // 做了符号扩展，保证计算的正确
            pc <= pc + 2 + $signed({{24{b1[7]}}, b1});
        end

        8'hff: begin
            $display("\n[CPU halted]");
            $finish;
        end

        default: begin
            $display("Invalid opcode %02x at PC %0d", opcode, pc);
            $finish;
        end

        endcase
      // $display("PC=%d opcode=%02x", pc, opcode);
    end

endmodule

section_3/arm7Cpu/tb.v
`timescale 1ns/1ps
module tb;

    reg clk = 0;

    always #5 clk = ~clk;

    simple_cpu cpu(.clk(clk));

    initial begin
        $dumpfile("wave.vcd");
        $dumpvars(0, tb);

        #200000;
        $display("Timeout");
        $finish;
    end

endmodule

section_3/arm7Cpu/wave.vcd
$date
	Mon Nov 17 18:35:35 2025
$end
$version
	Icarus Verilog
$end
$timescale
	1ps
$end
$scope module tb $end
$var reg 1 ! clk $end
$scope module cpu $end
$var wire 1 ! clk $end
$var reg 8 " b1 [7:0] $end
$var reg 8 # b2 [7:0] $end
$var reg 8 $ b3 [7:0] $end
$var reg 8 % opcode [7:0] $end
$var reg 32 & pc [31:0] $end
$var integer 32 ' i [31:0] $end
$upscope $end
$upscope $end
$enddefinitions $end
$comment Show the parameter values. $end
$dumpall
$end
#0
$dumpvars
b10000 '
b0 &
bx %
bx $
bx #
bx "
0!
$end
#5000
b11 &
b1001000 #
b0 "
b1 %
1!
#10000
0!
#15000
b101 &
b100 %
1!
#20000
0!
#25000
b1000 &
b1100101 #
b1 %
1!
#30000
0!
#35000
b1010 &
b100 %
1!
#40000
0!
#45000
b1101 &
b1101100 #
b1 %
1!
#50000
0!
#55000
b1111 &
b100 %
1!
#60000
0!
#65000
b10010 &
b1 %
1!
#70000
0!
#75000
b10100 &
b100 %
1!
#80000
0!
#85000
b10111 &
b1101111 #
b1 %
1!
#90000
0!
#95000
b11001 &
b100 %
1!
#100000
0!
#105000
b11100 &
b100000 #
b1 %
1!
#110000
0!
#115000
b11110 &
b100 %
1!
#120000
0!
#125000
b100001 &
b1010111 #
b1 %
1!
#130000
0!
#135000
b100011 &
b100 %
1!
#140000
0!
#145000
b100110 &
b1101111 #
b1 %
1!
#150000
0!
#155000
b101000 &
b100 %
1!
#160000
0!
#165000
b101011 &
b1110010 #
b1 %
1!
#170000
0!
#175000
b101101 &
b100 %
1!
#180000
0!
#185000
b110000 &
b1101100 #
b1 %
1!
#190000
0!
#195000
b110010 &
b100 %
1!
#200000
0!
#205000
b110101 &
b1100100 #
b1 %
1!
#210000
0!
#215000
b110111 &
b100 %
1!
#220000
0!
#225000
b111010 &
b1010 #
b1 %
1!
#230000
0!
#235000
b111100 &
b100 %
1!
#240000
0!
#245000
b11111111 %
1!
